{"data":{"popular_keywords":{"recommendation_type":"popular_keywords","title":"Lagi trending, nih","sub_title":"","keywords":[{"url":"https://www.tokopedia.com/find/keyboard-wireless?source=homepage.popular_keywords.0.0","image_url":"https://ecs7.tokopedia.net/img/cache/200-square/VqbcmM/2020/7/2/924c40fd-c6ac-4836-922c-6da93189f577.jpg","keyword":"Keyboard Wireless","product_count":324366,"product_count_formatted":"324,3 rb Produk","__typename":"Keyword"},{"url":"https://www.tokopedia.com/find/kompor-portable?source=homepage.popular_keywords.0.0","image_url":"https://ecs7.tokopedia.net/img/cache/200-square/product-1/2020/8/19/111477589/111477589_f11e5977-0679-46aa-a947-4657337ad2fb_700_700","keyword":"Kompor Portable","product_count":277396,"product_count_formatted":"277,3 rb Produk","__typename":"Keyword"},{"url":"https://www.tokopedia.com/find/kursi-kantor?source=homepage.popular_keywords.0.0","image_url":"https://images.tokopedia.net/img/cache/200-square/VqbcmM/2022/1/21/74c65f97-35db-4c39-80a2-8d32708208fe.jpg","keyword":"Kursi Kantor","product_count":244393,"product_count_formatted":"244,3 rb Produk","__typename":"Keyword"},{"url":"https://www.tokopedia.com/find/celana-kulot?source=homepage.popular_keywords.0.0","image_url":"https://ecs7.tokopedia.net/img/cache/200-square/product-1/2020/5/16/5056050/5056050_3e806055-cbd2-401f-ad37-c1ada6043d6f_1180_1180.jpg","keyword":"Celana Kulot","product_count":394891,"product_count_formatted":"394,8 rb Produk","__typename":"Keyword"}],"__typename":"PopularKeywords"}}}